WordCountinColumn/__init__.py
WordCountinColumn-1.0.3.dist-info/LICENSE.txt
WordCountinColumn-1.0.3.dist-info/METADATA
WordCountinColumn-1.0.3.dist-info/WHEEL
WordCountinColumn-1.0.3.dist-info/top_level.txt
WordCountinColumn-1.0.3.dist-info/RECORD
