Metadata-Version: 2.1
Name: WordCountinColumn
Version: 1.0.3
Summary: Count total number of appearance of words in a given pandas series
Home-page: https://github.com/HindyDS/Word-Count-in-Column
Author: Hindy Yuen
Author-email: hindy888@hotmail.com
License: MIT
Keywords: Words word count counting pandas
Platform: UNKNOWN
Classifier: Development Status :: 5 - Production/Stable
Classifier: Intended Audience :: Developers
Classifier: Topic :: Software Development :: Build Tools
Classifier: License :: OSI Approved :: MIT License
Classifier: Programming Language :: Python :: 3.7
Classifier: Programming Language :: Python :: 3.8
Classifier: Programming Language :: Python :: 3.9
Requires-Python: >=3.6
